setup.py
simplemodel/__init__.py
simplemodel/encode.py
simplemodel/fields.py
simplemodel/model.py
simplemodel.egg-info/PKG-INFO
simplemodel.egg-info/SOURCES.txt
simplemodel.egg-info/dependency_links.txt
simplemodel.egg-info/top_level.txt