Metadata-Version: 1.0
Name: simplemodel
Version: 0.1
Summary: Simple example-based models
Home-page: http://github.com/lann/simplemodel
Author: Lann Martin
Author-email: simplemodel@lannbox.com
License: MIT
Platform: UNKNOWN
